cosy/__init__.py
cosy/cli.py
cosy/cli_skel.py
cosy/cli_sysdeps.py
cosy/cli_version.py
cosy/install copy.py
cosy/install.py
cosy/packages.yml
cosy/proc.py
cosy/project.py
cosy/pylintrc
cosy/skel/__init__.py
cosy/skel/gitignore
cosy/tmp.py
cosy-0.5.0.dist-info/entry_points.txt
cosy-0.5.0.dist-info/LICENSE
cosy-0.5.0.dist-info/WHEEL
cosy-0.5.0.dist-info/METADATA
cosy-0.5.0.dist-info/RECORD
